pool_factory/__init__.py
pool_factory/factory.py
pool_factory-1.0.0.2.dist-info/METADATA
pool_factory-1.0.0.2.dist-info/WHEEL
pool_factory-1.0.0.2.dist-info/top_level.txt
pool_factory-1.0.0.2.dist-info/RECORD
